pyspark_data_profiler/__init__.py
pyspark_data_profiler/data_profiler/__init__.py
pyspark_data_profiler/data_profiler/profiler.py
pyspark_data_profiler/data_reader/__init__.py
pyspark_data_profiler/data_reader/reader.py
pyspark_data_profiler/utils/spark_setup_utils.py
pyspark_data_profiler-0.1.1.dist-info/LICENSE
pyspark_data_profiler-0.1.1.dist-info/METADATA
pyspark_data_profiler-0.1.1.dist-info/WHEEL
pyspark_data_profiler-0.1.1.dist-info/RECORD
