Metadata-Version: 2.1
Name: pyspark_data_profiler
Version: 0.1.1
Summary: Data profiling with PySpark
License: MIT
Author: Moises Salum
Requires-Python: >=3.9,<4.0
Classifier: License :: OSI Approved :: MIT License
Classifier: Programming Language :: Python :: 3
Classifier: Programming Language :: Python :: 3.9
Classifier: Programming Language :: Python :: 3.10
Classifier: Programming Language :: Python :: 3.11
Requires-Dist: pyspark (==3.5.0)
